thoa/__init__.py
thoa/cli/__init__.py
thoa/cli/commands/goodbye_world.py
thoa/cli/commands/hello_world.py
thoa/cli/commands/jobs.py
thoa/cli/commands/run.py
thoa/cli/commands/tools.py
thoa/cli/dataset_app.py
thoa/config/__init__.py
thoa/config/config.py
thoa/core/__init__.py
thoa/core/api_utils.py
thoa/core/dataset_utils.py
thoa/core/env_utils.py
thoa/core/file_utils.py
thoa/core/job_utils.py
thoa/entrypoint.py
thoa-0.1.2.dist-info/METADATA
thoa-0.1.2.dist-info/WHEEL
thoa-0.1.2.dist-info/entry_points.txt
thoa-0.1.2.dist-info/licenses/LICENSE
thoa-0.1.2.dist-info/RECORD
