Metadata-Version: 2.4
Name: thoa
Version: 0.1.2
Summary: Thoa Command Line Interface for Remote Job Submission
License: MIT
License-File: LICENSE
Author: GWC GmbH
Author-email: hello@gwc-solutions.ch
Requires-Python: >=3.9,<4.0
Classifier: License :: OSI Approved :: MIT License
Classifier: Programming Language :: Python :: 3
Classifier: Programming Language :: Python :: 3.9
Classifier: Programming Language :: Python :: 3.10
Classifier: Programming Language :: Python :: 3.11
Classifier: Programming Language :: Python :: 3.12
Classifier: Programming Language :: Python :: 3.13
Classifier: Programming Language :: Python :: 3.14
Requires-Dist: azure-storage-blob (>=12.26.0,<13.0.0)
Requires-Dist: httpx (>=0.28.1,<0.29.0)
Requires-Dist: pydantic-settings (>=2.10.1,<3.0.0)
Requires-Dist: typer (>=0.16.0,<0.17.0)
Requires-Dist: typing-extensions (>=4.14.1,<5.0.0)
Requires-Dist: websockets (>=15.0.1,<16.0.0)
